{
   "id": "12",
   "maps": [
      {
         "type": "scenario",
         "page": 16,
         "name": 16,
         "results": [
            {
               "name": "16-C",
               "variant": "",
               "orientation": "-180",
               "type": "tile",
               "results": [
                  {
                     "position": {
                        "x": 1184,
                        "y": 1878
                     },
                     "size": {
                        "x": 80,
                        "y": 33
                     },
                     "score": 0.9999996423721313
                  }
               ]
            },
            {
               "name": "Ancient Artillery",
               "type": "monster",
               "results": [
                  {
                     "position": {
                        "x": 1458,
                        "y": 1921
                     },
                     "size": {
                        "x": 111,
                        "y": 133
                     },
                     "score": 0.997439980506897
                  },
                  {
                     "position": {
                        "x": 1723,
                        "y": 1921
                     },
                     "size": {
                        "x": 111,
                        "y": 133
                     },
                     "score": 0.9974421262741089
                  },
                  {
                     "position": {
                        "x": 1988,
                        "y": 1921
                     },
                     "size": {
                        "x": 111,
                        "y": 133
                     },
                     "score": 0.9974432587623596
                  },
                  {
                     "position": {
                        "x": 1458,
                        "y": 2611
                     },
                     "size": {
                        "x": 111,
                        "y": 133
                     },
                     "score": 0.9966919422149658
                  },
                  {
                     "position": {
                        "x": 1723,
                        "y": 2611
                     },
                     "size": {
                        "x": 111,
                        "y": 133
                     },
                     "score": 0.9966950416564941
                  },
                  {
                     "position": {
                        "x": 1988,
                        "y": 2611
                     },
                     "size": {
                        "x": 111,
                        "y": 133
                     },
                     "score": 0.9966962933540344
                  }
               ]
            },
            {
               "name": "Dungeon Door",
               "orientation": "-270",
               "type": "overlay",
               "results": [
                  {
                     "position": {
                        "x": 2202,
                        "y": 2281
                     },
                     "size": {
                        "x": 79,
                        "y": 106
                     },
                     "score": 0.999998927116394
                  }
               ]
            },
            {
               "name": "Barricade",
               "orientation": "-60",
               "type": "overlay",
               "results": [
                  {
                     "position": {
                        "x": 1372,
                        "y": 2518
                     },
                     "size": {
                        "x": 122,
                        "y": 190
                     },
                     "score": 1.0
                  },
                  {
                     "position": {
                        "x": 1637,
                        "y": 2518
                     },
                     "size": {
                        "x": 122,
                        "y": 190
                     },
                     "score": 0.9964602589607239
                  },
                  {
                     "position": {
                        "x": 1902,
                        "y": 2518
                     },
                     "size": {
                        "x": 122,
                        "y": 190
                     },
                     "score": 0.9997082948684692
                  }
               ]
            },
            {
               "name": "Barricade",
               "orientation": "-60",
               "type": "overlay",
               "results": [
                  {
                     "position": {
                        "x": 1324,
                        "y": 2508
                     },
                     "size": {
                        "x": 174,
                        "y": 206
                     },
                     "score": 0.9898122549057007
                  },
                  {
                     "position": {
                        "x": 1589,
                        "y": 2508
                     },
                     "size": {
                        "x": 174,
                        "y": 206
                     },
                     "score": 0.9822708368301392
                  },
                  {
                     "position": {
                        "x": 1854,
                        "y": 2508
                     },
                     "size": {
                        "x": 174,
                        "y": 206
                     },
                     "score": 0.9891130924224854
                  }
               ]
            },
            {
               "name": "Barricade",
               "orientation": "-300",
               "type": "overlay",
               "results": [
                  {
                     "position": {
                        "x": 1335,
                        "y": 1955
                     },
                     "size": {
                        "x": 137,
                        "y": 181
                     },
                     "score": 1.0000016689300537
                  },
                  {
                     "position": {
                        "x": 1600,
                        "y": 1955
                     },
                     "size": {
                        "x": 137,
                        "y": 181
                     },
                     "score": 0.998508632183075
                  },
                  {
                     "position": {
                        "x": 1865,
                        "y": 1955
                     },
                     "size": {
                        "x": 137,
                        "y": 181
                     },
                     "score": 0.99173504114151
                  }
               ]
            },
            {
               "name": "Debris",
               "orientation": "",
               "type": "overlay",
               "results": [
                  {
                     "position": {
                        "x": 1198,
                        "y": 1939
                     },
                     "size": {
                        "x": 98,
                        "y": 95
                     },
                     "score": 0.9736691117286682
                  },
                  {
                     "position": {
                        "x": 2125,
                        "y": 1939
                     },
                     "size": {
                        "x": 98,
                        "y": 95
                     },
                     "score": 0.9864015579223633
                  },
                  {
                     "position": {
                        "x": 1197,
                        "y": 2628
                     },
                     "size": {
                        "x": 98,
                        "y": 95
                     },
                     "score": 0.9924613237380981
                  },
                  {
                     "position": {
                        "x": 2125,
                        "y": 2628
                     },
                     "size": {
                        "x": 98,
                        "y": 95
                     },
                     "score": 0.9985703229904175
                  }
               ]
            },
            {
               "name": "ane.png",
               "type": "monster levels",
               "results": [
                  {
                     "position": {
                        "x": 1450,
                        "y": 1954
                     },
                     "size": {
                        "x": 29,
                        "y": 83
                     },
                     "score": 0.9985824227333069
                  },
                  {
                     "position": {
                        "x": 1450,
                        "y": 2643
                     },
                     "size": {
                        "x": 29,
                        "y": 83
                     },
                     "score": 0.9882968068122864
                  }
               ]
            },
            {
               "name": "eee.png",
               "type": "monster levels",
               "results": [
                  {
                     "position": {
                        "x": 1719,
                        "y": 1963
                     },
                     "size": {
                        "x": 21,
                        "y": 67
                     },
                     "score": 0.9898122549057007
                  },
                  {
                     "position": {
                        "x": 1720,
                        "y": 2653
                     },
                     "size": {
                        "x": 21,
                        "y": 67
                     },
                     "score": 0.9929723739624023
                  }
               ]
            },
            {
               "name": "nee.png",
               "type": "monster levels",
               "results": [
                  {
                     "position": {
                        "x": 1986,
                        "y": 2648
                     },
                     "size": {
                        "x": 21,
                        "y": 76
                     },
                     "score": 0.9926152229309082
                  }
               ]
            },
            {
               "name": "nne.png",
               "type": "monster levels",
               "results": [
                  {
                     "position": {
                        "x": 1984,
                        "y": 1958
                     },
                     "size": {
                        "x": 23,
                        "y": 76
                     },
                     "score": 0.9997386932373047
                  }
               ]
            },
            {
               "name": "Door.png",
               "type": "overlay types",
               "results": [
                  {
                     "position": {
                        "x": 2225,
                        "y": 2369
                     },
                     "size": {
                        "x": 28,
                        "y": 31
                     },
                     "score": 0.9821778535842896
                  }
               ]
            },
            {
               "name": "Obstacle-2.png",
               "type": "overlay types",
               "results": [
                  {
                     "position": {
                        "x": 1231,
                        "y": 2025
                     },
                     "size": {
                        "x": 26,
                        "y": 29
                     },
                     "score": 0.9567779302597046
                  },
                  {
                     "position": {
                        "x": 2159,
                        "y": 2025
                     },
                     "size": {
                        "x": 26,
                        "y": 29
                     },
                     "score": 0.9576811194419861
                  },
                  {
                     "position": {
                        "x": 1431,
                        "y": 2140
                     },
                     "size": {
                        "x": 26,
                        "y": 29
                     },
                     "score": 0.9741489291191101
                  },
                  {
                     "position": {
                        "x": 1696,
                        "y": 2140
                     },
                     "size": {
                        "x": 26,
                        "y": 29
                     },
                     "score": 0.9889286756515503
                  },
                  {
                     "position": {
                        "x": 1961,
                        "y": 2140
                     },
                     "size": {
                        "x": 26,
                        "y": 29
                     },
                     "score": 0.9989590048789978
                  },
                  {
                     "position": {
                        "x": 1231,
                        "y": 2714
                     },
                     "size": {
                        "x": 26,
                        "y": 29
                     },
                     "score": 0.9558702707290649
                  },
                  {
                     "position": {
                        "x": 1365,
                        "y": 2714
                     },
                     "size": {
                        "x": 26,
                        "y": 29
                     },
                     "score": 0.9832349419593811
                  },
                  {
                     "position": {
                        "x": 1630,
                        "y": 2714
                     },
                     "size": {
                        "x": 26,
                        "y": 29
                     },
                     "score": 0.9978230595588684
                  },
                  {
                     "position": {
                        "x": 1895,
                        "y": 2714
                     },
                     "size": {
                        "x": 26,
                        "y": 29
                     },
                     "score": 0.986426830291748
                  },
                  {
                     "position": {
                        "x": 2159,
                        "y": 2714
                     },
                     "size": {
                        "x": 26,
                        "y": 29
                     },
                     "score": 0.9467366933822632
                  }
               ]
            },
            {
               "name": "Obstacle.png",
               "type": "overlay types",
               "results": [
                  {
                     "position": {
                        "x": 1232,
                        "y": 2025
                     },
                     "size": {
                        "x": 27,
                        "y": 30
                     },
                     "score": 0.9963410496711731
                  },
                  {
                     "position": {
                        "x": 2159,
                        "y": 2025
                     },
                     "size": {
                        "x": 27,
                        "y": 30
                     },
                     "score": 0.9762775897979736
                  },
                  {
                     "position": {
                        "x": 1431,
                        "y": 2140
                     },
                     "size": {
                        "x": 27,
                        "y": 30
                     },
                     "score": 0.9666499495506287
                  },
                  {
                     "position": {
                        "x": 1696,
                        "y": 2140
                     },
                     "size": {
                        "x": 27,
                        "y": 30
                     },
                     "score": 0.9586101174354553
                  },
                  {
                     "position": {
                        "x": 1962,
                        "y": 2140
                     },
                     "size": {
                        "x": 27,
                        "y": 30
                     },
                     "score": 0.950730562210083
                  },
                  {
                     "position": {
                        "x": 1232,
                        "y": 2714
                     },
                     "size": {
                        "x": 27,
                        "y": 30
                     },
                     "score": 0.9768775105476379
                  },
                  {
                     "position": {
                        "x": 1365,
                        "y": 2714
                     },
                     "size": {
                        "x": 27,
                        "y": 30
                     },
                     "score": 0.962806761264801
                  },
                  {
                     "position": {
                        "x": 1631,
                        "y": 2714
                     },
                     "size": {
                        "x": 27,
                        "y": 30
                     },
                     "score": 0.9436168074607849
                  },
                  {
                     "position": {
                        "x": 1895,
                        "y": 2714
                     },
                     "size": {
                        "x": 27,
                        "y": 30
                     },
                     "score": 0.960635781288147
                  },
                  {
                     "position": {
                        "x": 2159,
                        "y": 2714
                     },
                     "size": {
                        "x": 27,
                        "y": 30
                     },
                     "score": 0.9893512725830078
                  }
               ]
            },
            {
               "name": "1.png",
               "type": "tokens",
               "results": [
                  {
                     "position": {
                        "x": 2219,
                        "y": 2304
                     },
                     "size": {
                        "x": 40,
                        "y": 51
                     },
                     "score": 1.0
                  }
               ]
            },
            {
               "name": "1g.png",
               "type": "tokens",
               "results": [
                  {
                     "position": {
                        "x": 2216,
                        "y": 2308
                     },
                     "size": {
                        "x": 48,
                        "y": 45
                     },
                     "score": 0.9502732157707214
                  }
               ]
            },
            {
               "name": "start.png",
               "type": "tokens",
               "results": [
                  {
                     "position": {
                        "x": 1292,
                        "y": 2079
                     },
                     "size": {
                        "x": 44,
                        "y": 45
                     },
                     "score": 0.9979082345962524
                  },
                  {
                     "position": {
                        "x": 1224,
                        "y": 2193
                     },
                     "size": {
                        "x": 44,
                        "y": 45
                     },
                     "score": 0.9710327386856079
                  },
                  {
                     "position": {
                        "x": 1292,
                        "y": 2308
                     },
                     "size": {
                        "x": 44,
                        "y": 45
                     },
                     "score": 0.9879053831100464
                  },
                  {
                     "position": {
                        "x": 1224,
                        "y": 2422
                     },
                     "size": {
                        "x": 44,
                        "y": 45
                     },
                     "score": 0.9869837164878845
                  },
                  {
                     "position": {
                        "x": 1292,
                        "y": 2537
                     },
                     "size": {
                        "x": 44,
                        "y": 45
                     },
                     "score": 0.9964625835418701
                  }
               ]
            }
         ]
      },
      {
         "type": "section",
         "page": 34,
         "name": "34.1",
         "results": [
            {
               "name": "11-E",
               "variant": "",
               "orientation": "-300",
               "type": "tile",
               "results": [
                  {
                     "position": {
                        "x": 1252,
                        "y": 1487
                     },
                     "size": {
                        "x": 55,
                        "y": 67
                     },
                     "score": 1.000001072883606
                  }
               ]
            },
            {
               "name": "15-C",
               "variant": "",
               "orientation": "-0",
               "type": "tile",
               "results": [
                  {
                     "position": {
                        "x": 2140,
                        "y": 1302
                     },
                     "size": {
                        "x": 76,
                        "y": 29
                     },
                     "score": 0.9739800095558167
                  }
               ]
            },
            {
               "name": "Ancient Artillery",
               "type": "monster",
               "results": [
                  {
                     "position": {
                        "x": 2092,
                        "y": 468
                     },
                     "size": {
                        "x": 111,
                        "y": 133
                     },
                     "score": 0.9975792169570923
                  },
                  {
                     "position": {
                        "x": 2092,
                        "y": 1155
                     },
                     "size": {
                        "x": 111,
                        "y": 133
                     },
                     "score": 0.9950294494628906
                  }
               ]
            },
            {
               "name": "Night Demon",
               "type": "monster",
               "results": [
                  {
                     "position": {
                        "x": 1498,
                        "y": 355
                     },
                     "size": {
                        "x": 109,
                        "y": 128
                     },
                     "score": 0.9987767338752747
                  },
                  {
                     "position": {
                        "x": 1166,
                        "y": 470
                     },
                     "size": {
                        "x": 109,
                        "y": 128
                     },
                     "score": 0.9947496652603149
                  },
                  {
                     "position": {
                        "x": 1232,
                        "y": 814
                     },
                     "size": {
                        "x": 109,
                        "y": 128
                     },
                     "score": 0.9851706027984619
                  },
                  {
                     "position": {
                        "x": 1166,
                        "y": 1158
                     },
                     "size": {
                        "x": 109,
                        "y": 128
                     },
                     "score": 0.9910354018211365
                  },
                  {
                     "position": {
                        "x": 1497,
                        "y": 1273
                     },
                     "size": {
                        "x": 109,
                        "y": 128
                     },
                     "score": 0.991571843624115
                  }
               ]
            },
            {
               "name": "Steel Automaton",
               "type": "monster",
               "results": [
                  {
                     "position": {
                        "x": 1962,
                        "y": 700
                     },
                     "size": {
                        "x": 105,
                        "y": 127
                     },
                     "score": 0.9929572343826294
                  },
                  {
                     "position": {
                        "x": 1896,
                        "y": 815
                     },
                     "size": {
                        "x": 105,
                        "y": 127
                     },
                     "score": 0.9921460747718811
                  },
                  {
                     "position": {
                        "x": 1962,
                        "y": 930
                     },
                     "size": {
                        "x": 105,
                        "y": 127
                     },
                     "score": 0.9913597106933594
                  }
               ]
            },
            {
               "name": "Large Dungeon Corridor",
               "orientation": "-60",
               "type": "overlay",
               "results": [
                  {
                     "position": {
                        "x": 1502,
                        "y": 480
                     },
                     "size": {
                        "x": 160,
                        "y": 211
                     },
                     "score": 0.9767345786094666
                  }
               ]
            },
            {
               "name": "Large Dungeon Corridor",
               "orientation": "-300",
               "type": "overlay",
               "results": [
                  {
                     "position": {
                        "x": 1499,
                        "y": 1054
                     },
                     "size": {
                        "x": 164,
                        "y": 216
                     },
                     "score": 0.9936917424201965
                  }
               ]
            },
            {
               "name": "Bear Trap",
               "orientation": "",
               "type": "overlay",
               "results": [
                  {
                     "position": {
                        "x": 1837,
                        "y": 480
                     },
                     "size": {
                        "x": 85,
                        "y": 97
                     },
                     "score": 0.9805086255073547
                  },
                  {
                     "position": {
                        "x": 1241,
                        "y": 596
                     },
                     "size": {
                        "x": 85,
                        "y": 97
                     },
                     "score": 0.9815927147865295
                  },
                  {
                     "position": {
                        "x": 1373,
                        "y": 596
                     },
                     "size": {
                        "x": 85,
                        "y": 97
                     },
                     "score": 0.9613096714019775
                  },
                  {
                     "position": {
                        "x": 1241,
                        "y": 1055
                     },
                     "size": {
                        "x": 85,
                        "y": 97
                     },
                     "score": 0.9747366309165955
                  },
                  {
                     "position": {
                        "x": 1373,
                        "y": 1055
                     },
                     "size": {
                        "x": 85,
                        "y": 97
                     },
                     "score": 0.9547397494316101
                  },
                  {
                     "position": {
                        "x": 1837,
                        "y": 1168
                     },
                     "size": {
                        "x": 85,
                        "y": 97
                     },
                     "score": 0.9891709089279175
                  }
               ]
            },
            {
               "name": "Bear Trap",
               "orientation": "-0",
               "type": "overlay",
               "results": [
                  {
                     "position": {
                        "x": 1833,
                        "y": 475
                     },
                     "size": {
                        "x": 90,
                        "y": 106
                     },
                     "score": 0.990027129650116
                  },
                  {
                     "position": {
                        "x": 1237,
                        "y": 591
                     },
                     "size": {
                        "x": 90,
                        "y": 106
                     },
                     "score": 0.9702004194259644
                  },
                  {
                     "position": {
                        "x": 1369,
                        "y": 591
                     },
                     "size": {
                        "x": 90,
                        "y": 106
                     },
                     "score": 0.9806900024414062
                  },
                  {
                     "position": {
                        "x": 1237,
                        "y": 1049
                     },
                     "size": {
                        "x": 90,
                        "y": 106
                     },
                     "score": 0.9695992469787598
                  },
                  {
                     "position": {
                        "x": 1369,
                        "y": 1049
                     },
                     "size": {
                        "x": 90,
                        "y": 106
                     },
                     "score": 0.9794641733169556
                  },
                  {
                     "position": {
                        "x": 1833,
                        "y": 1163
                     },
                     "size": {
                        "x": 90,
                        "y": 106
                     },
                     "score": 0.9942848682403564
                  }
               ]
            },
            {
               "name": "Bear Trap",
               "orientation": "-0",
               "type": "overlay",
               "results": [
                  {
                     "position": {
                        "x": 1842,
                        "y": 505
                     },
                     "size": {
                        "x": 75,
                        "y": 56
                     },
                     "score": 0.9830235242843628
                  },
                  {
                     "position": {
                        "x": 1245,
                        "y": 620
                     },
                     "size": {
                        "x": 75,
                        "y": 56
                     },
                     "score": 0.9932319521903992
                  },
                  {
                     "position": {
                        "x": 1378,
                        "y": 620
                     },
                     "size": {
                        "x": 75,
                        "y": 56
                     },
                     "score": 0.9985044598579407
                  },
                  {
                     "position": {
                        "x": 1245,
                        "y": 1079
                     },
                     "size": {
                        "x": 75,
                        "y": 56
                     },
                     "score": 0.9947136640548706
                  },
                  {
                     "position": {
                        "x": 1378,
                        "y": 1079
                     },
                     "size": {
                        "x": 75,
                        "y": 56
                     },
                     "score": 1.0000001192092896
                  },
                  {
                     "position": {
                        "x": 1842,
                        "y": 1193
                     },
                     "size": {
                        "x": 75,
                        "y": 56
                     },
                     "score": 0.9768086671829224
                  }
               ]
            },
            {
               "name": "Rubble",
               "orientation": "",
               "type": "overlay",
               "results": [
                  {
                     "position": {
                        "x": 1238,
                        "y": 370
                     },
                     "size": {
                        "x": 91,
                        "y": 76
                     },
                     "score": 0.9954016208648682
                  },
                  {
                     "position": {
                        "x": 1701,
                        "y": 711
                     },
                     "size": {
                        "x": 91,
                        "y": 76
                     },
                     "score": 0.9587521553039551
                  },
                  {
                     "position": {
                        "x": 1437,
                        "y": 1173
                     },
                     "size": {
                        "x": 91,
                        "y": 76
                     },
                     "score": 0.9824775457382202
                  }
               ]
            },
            {
               "name": "Rubble",
               "orientation": "-0",
               "type": "overlay",
               "results": [
                  {
                     "position": {
                        "x": 1245,
                        "y": 389
                     },
                     "size": {
                        "x": 82,
                        "y": 58
                     },
                     "score": 0.9478271007537842
                  },
                  {
                     "position": {
                        "x": 1709,
                        "y": 731
                     },
                     "size": {
                        "x": 82,
                        "y": 58
                     },
                     "score": 0.9494433999061584
                  },
                  {
                     "position": {
                        "x": 1444,
                        "y": 1192
                     },
                     "size": {
                        "x": 82,
                        "y": 58
                     },
                     "score": 0.955278754234314
                  }
               ]
            },
            {
               "name": "Treasure Chest",
               "orientation": "",
               "type": "overlay",
               "results": [
                  {
                     "position": {
                        "x": 2159,
                        "y": 843
                     },
                     "size": {
                        "x": 107,
                        "y": 49
                     },
                     "score": 0.995100200176239
                  }
               ]
            },
            {
               "name": "aae.png",
               "type": "monster levels",
               "results": [
                  {
                     "position": {
                        "x": 1955,
                        "y": 736
                     },
                     "size": {
                        "x": 24,
                        "y": 76
                     },
                     "score": 0.9896202087402344
                  },
                  {
                     "position": {
                        "x": 1955,
                        "y": 965
                     },
                     "size": {
                        "x": 24,
                        "y": 76
                     },
                     "score": 0.9912679195404053
                  }
               ]
            },
            {
               "name": "aan.png",
               "type": "monster levels",
               "results": [
                  {
                     "position": {
                        "x": 1489,
                        "y": 1306
                     },
                     "size": {
                        "x": 26,
                        "y": 81
                     },
                     "score": 0.9996435046195984
                  }
               ]
            },
            {
               "name": "aans.png",
               "type": "monster levels",
               "results": [
                  {
                     "position": {
                        "x": 1493,
                        "y": 1315
                     },
                     "size": {
                        "x": 23,
                        "y": 69
                     },
                     "score": 0.9424572587013245
                  }
               ]
            },
            {
               "name": "ann.png",
               "type": "monster levels",
               "results": [
                  {
                     "position": {
                        "x": 1159,
                        "y": 507
                     },
                     "size": {
                        "x": 24,
                        "y": 75
                     },
                     "score": 0.9930079579353333
                  }
               ]
            },
            {
               "name": "eea.png",
               "type": "monster levels",
               "results": [
                  {
                     "position": {
                        "x": 1887,
                        "y": 845
                     },
                     "size": {
                        "x": 28,
                        "y": 83
                     },
                     "score": 0.9984497427940369
                  }
               ]
            },
            {
               "name": "nee.png",
               "type": "monster levels",
               "results": [
                  {
                     "position": {
                        "x": 2088,
                        "y": 504
                     },
                     "size": {
                        "x": 21,
                        "y": 76
                     },
                     "score": 0.9941501617431641
                  },
                  {
                     "position": {
                        "x": 1227,
                        "y": 849
                     },
                     "size": {
                        "x": 21,
                        "y": 76
                     },
                     "score": 0.9935858249664307
                  },
                  {
                     "position": {
                        "x": 2089,
                        "y": 1192
                     },
                     "size": {
                        "x": 21,
                        "y": 76
                     },
                     "score": 0.9960694909095764
                  }
               ]
            },
            {
               "name": "nna.png",
               "type": "monster levels",
               "results": [
                  {
                     "position": {
                        "x": 1158,
                        "y": 1215
                     },
                     "size": {
                        "x": 27,
                        "y": 81
                     },
                     "score": 0.9405080676078796
                  }
               ]
            },
            {
               "name": "nnn.png",
               "type": "monster levels",
               "results": [
                  {
                     "position": {
                        "x": 1490,
                        "y": 387
                     },
                     "size": {
                        "x": 24,
                        "y": 83
                     },
                     "score": 0.9809677600860596
                  },
                  {
                     "position": {
                        "x": 1159,
                        "y": 1190
                     },
                     "size": {
                        "x": 24,
                        "y": 83
                     },
                     "score": 0.9794696569442749
                  }
               ]
            },
            {
               "name": "Corridor-2.png",
               "type": "overlay types",
               "results": [
                  {
                     "position": {
                        "x": 1537,
                        "y": 686
                     },
                     "size": {
                        "x": 26,
                        "y": 30
                     },
                     "score": 0.9520465135574341
                  },
                  {
                     "position": {
                        "x": 1601,
                        "y": 1260
                     },
                     "size": {
                        "x": 26,
                        "y": 30
                     },
                     "score": 0.9687088131904602
                  }
               ]
            },
            {
               "name": "Difficult Terrain.png",
               "type": "overlay types",
               "results": [
                  {
                     "position": {
                        "x": 1270,
                        "y": 458
                     },
                     "size": {
                        "x": 26,
                        "y": 29
                     },
                     "score": 0.9709064960479736
                  },
                  {
                     "position": {
                        "x": 1734,
                        "y": 801
                     },
                     "size": {
                        "x": 26,
                        "y": 29
                     },
                     "score": 0.9551321268081665
                  },
                  {
                     "position": {
                        "x": 1469,
                        "y": 1261
                     },
                     "size": {
                        "x": 26,
                        "y": 29
                     },
                     "score": 0.9650437235832214
                  }
               ]
            },
            {
               "name": "Door.png",
               "type": "overlay types",
               "results": [
                  {
                     "position": {
                        "x": 1004,
                        "y": 915
                     },
                     "size": {
                        "x": 28,
                        "y": 31
                     },
                     "score": 0.980866551399231
                  }
               ]
            },
            {
               "name": "Trap.png",
               "type": "overlay types",
               "results": [
                  {
                     "position": {
                        "x": 1868,
                        "y": 573
                     },
                     "size": {
                        "x": 24,
                        "y": 28
                     },
                     "score": 0.9788715839385986
                  },
                  {
                     "position": {
                        "x": 1271,
                        "y": 688
                     },
                     "size": {
                        "x": 24,
                        "y": 28
                     },
                     "score": 0.9948381185531616
                  },
                  {
                     "position": {
                        "x": 1404,
                        "y": 688
                     },
                     "size": {
                        "x": 24,
                        "y": 28
                     },
                     "score": 0.9999995231628418
                  },
                  {
                     "position": {
                        "x": 1271,
                        "y": 1147
                     },
                     "size": {
                        "x": 24,
                        "y": 28
                     },
                     "score": 0.9931515455245972
                  },
                  {
                     "position": {
                        "x": 1404,
                        "y": 1147
                     },
                     "size": {
                        "x": 24,
                        "y": 28
                     },
                     "score": 0.9983278512954712
                  },
                  {
                     "position": {
                        "x": 1868,
                        "y": 1260
                     },
                     "size": {
                        "x": 24,
                        "y": 28
                     },
                     "score": 0.9712515473365784
                  }
               ]
            },
            {
               "name": "Treasure.png",
               "type": "overlay types",
               "results": [
                  {
                     "position": {
                        "x": 2196,
                        "y": 811
                     },
                     "size": {
                        "x": 27,
                        "y": 29
                     },
                     "score": 0.9465579390525818
                  }
               ]
            },
            {
               "name": "1.png",
               "type": "tokens",
               "results": [
                  {
                     "position": {
                        "x": 998,
                        "y": 848
                     },
                     "size": {
                        "x": 40,
                        "y": 51
                     },
                     "score": 0.9476549029350281
                  }
               ]
            },
            {
               "name": "1g.png",
               "type": "tokens",
               "results": [
                  {
                     "position": {
                        "x": 995,
                        "y": 852
                     },
                     "size": {
                        "x": 48,
                        "y": 45
                     },
                     "score": 0.9999969601631165
                  }
               ]
            }
         ]
      }
   ],
   "layout": [
      {
         "name": "11-E",
         "orientation": "-300",
         "variant": "",
         "positions": [
            {
               "position": {
                  "x": 1152,
                  "y": 679
               },
               "size": {
                  "x": 298,
                  "y": 308
               },
               "score": 0.9999999403953552
            }
         ]
      },
      {
         "name": "15-C",
         "orientation": "-0",
         "variant": "",
         "positions": [
            {
               "position": {
                  "x": 1332,
                  "y": 731
               },
               "size": {
                  "x": 174,
                  "y": 200
               },
               "score": 1.0000008344650269
            }
         ]
      },
      {
         "name": "16-C",
         "orientation": "-180",
         "variant": "",
         "positions": [
            {
               "position": {
                  "x": 976,
                  "y": 733
               },
               "size": {
                  "x": 233,
                  "y": 200
               },
               "score": 0.9539393186569214
            }
         ]
      }
   ]
}