{
   "page": 63,
   "results": [
      {
         "name": "02-J",
         "type": "tile",
         "results": [
            {
               "position": {
                  "x": 1856,
                  "y": 2900
               },
               "score": 1.000000238418579
            }
         ],
         "orientation": "-0"
      },
      {
         "name": "02-L",
         "type": "tile",
         "results": [
            {
               "position": {
                  "x": 2390,
                  "y": 2899
               },
               "score": 0.9999998807907104
            }
         ],
         "orientation": "-0"
      },
      {
         "name": "Cave Door",
         "type": "overlay",
         "results": [
            {
               "position": {
                  "x": 1628,
                  "y": 2306
               },
               "score": 0.9967146515846252
            }
         ]
      },
      {
         "name": "Large Cave Corridor",
         "type": "overlay",
         "results": [
            {
               "position": {
                  "x": 1825,
                  "y": 2460
               },
               "score": 0.9783869385719299
            },
            {
               "position": {
                  "x": 1825,
                  "y": 2690
               },
               "score": 0.9912400841712952
            }
         ]
      },
      {
         "name": "Cave Corridor",
         "type": "overlay",
         "results": [
            {
               "position": {
                  "x": 1894,
                  "y": 2564
               },
               "score": 0.9755249619483948
            },
            {
               "position": {
                  "x": 1894,
                  "y": 2793
               },
               "score": 1.0000087022781372
            }
         ]
      },
      {
         "name": "Ice Pillar",
         "type": "overlay",
         "results": [
            {
               "position": {
                  "x": 2376,
                  "y": 2431
               },
               "score": 0.9909626841545105
            },
            {
               "position": {
                  "x": 1713,
                  "y": 2660
               },
               "score": 0.9909220337867737
            },
            {
               "position": {
                  "x": 2243,
                  "y": 2660
               },
               "score": 0.990364134311676
            },
            {
               "position": {
                  "x": 2309,
                  "y": 2775
               },
               "score": 0.990949809551239
            }
         ]
      },
      {
         "name": "Large Cave Rock",
         "type": "overlay",
         "results": [
            {
               "position": {
                  "x": 1467,
                  "y": 2462
               },
               "score": 0.9996549487113953
            }
         ]
      },
      {
         "name": "Large Cave Rock",
         "type": "overlay",
         "results": [
            {
               "position": {
                  "x": 2047,
                  "y": 2443
               },
               "score": 0.9987886548042297
            }
         ]
      },
      {
         "name": "Large Cave Rock",
         "type": "overlay",
         "results": [
            {
               "position": {
                  "x": 1440,
                  "y": 2682
               },
               "score": 0.9999995231628418
            }
         ]
      },
      {
         "name": "Corridor.png",
         "type": "overlay types",
         "results": [
            {
               "position": {
                  "x": 1928,
                  "y": 2861
               },
               "score": 0.9681862592697144
            }
         ]
      },
      {
         "name": "Objective-2.png",
         "type": "overlay types",
         "results": [
            {
               "position": {
                  "x": 1599,
                  "y": 2517
               },
               "score": 1.0000009536743164
            },
            {
               "position": {
                  "x": 2394,
                  "y": 2517
               },
               "score": 0.9525665640830994
            },
            {
               "position": {
                  "x": 2063,
                  "y": 2632
               },
               "score": 0.9981238842010498
            },
            {
               "position": {
                  "x": 2261,
                  "y": 2746
               },
               "score": 0.9536715745925903
            },
            {
               "position": {
                  "x": 1533,
                  "y": 2861
               },
               "score": 0.9785066843032837
            }
         ]
      },
      {
         "name": "Objective.png",
         "type": "overlay types",
         "results": [
            {
               "position": {
                  "x": 2393,
                  "y": 2517
               },
               "score": 0.9965298771858215
            },
            {
               "position": {
                  "x": 1729,
                  "y": 2746
               },
               "score": 0.9604427218437195
            },
            {
               "position": {
                  "x": 2260,
                  "y": 2746
               },
               "score": 0.9914289712905884
            },
            {
               "position": {
                  "x": 2326,
                  "y": 2861
               },
               "score": 0.9823533296585083
            }
         ]
      },
      {
         "name": "1.png",
         "type": "tokens",
         "results": [
            {
               "position": {
                  "x": 1657,
                  "y": 2330
               },
               "score": 1.0
            }
         ]
      },
      {
         "name": "1g.png",
         "type": "tokens",
         "results": [
            {
               "position": {
                  "x": 1654,
                  "y": 2334
               },
               "score": 0.9502014517784119
            }
         ]
      },
      {
         "name": "start.png",
         "type": "tokens",
         "results": [
            {
               "position": {
                  "x": 1790,
                  "y": 2803
               },
               "score": 0.9957326650619507
            },
            {
               "position": {
                  "x": 2055,
                  "y": 2803
               },
               "score": 0.995660126209259
            }
         ]
      },
      {
         "name": "starts.png",
         "type": "tokens",
         "results": [
            {
               "position": {
                  "x": 1856,
                  "y": 2685
               },
               "score": 0.999071478843689
            },
            {
               "position": {
                  "x": 1986,
                  "y": 2685
               },
               "score": 0.9795261025428772
            },
            {
               "position": {
                  "x": 1922,
                  "y": 2797
               },
               "score": 1.0
            }
         ]
      }
   ]
}